fluidsim_ocean/__init__.py
fluidsim_ocean/_version.py
fluidsim_ocean/sw2l/__init__.py
fluidsim_ocean/sw2l/solver.py
fluidsim_ocean/sw2l/state.py
fluidsim_ocean-0.0.0a0.dist-info/METADATA
fluidsim_ocean-0.0.0a0.dist-info/RECORD
fluidsim_ocean-0.0.0a0.dist-info/WHEEL
fluidsim_ocean-0.0.0a0.dist-info/entry_points.txt
fluidsim_ocean-0.0.0a0.dist-info/top_level.txt
