Metadata-Version: 2.1
Name: fluidsim-ocean
Version: 0.0.0a0
Summary: Fluidsim solvers for oceanic studies.
Home-page: https://bitbucket.org/fluiddyn/fluidsim_ocean
Author: Pierre Augier
Author-email: pierre.augier@univ-grenoble-alpes.fr
License: CeCILL
Keywords: Fluid dynamics,research
Platform: UNKNOWN
Classifier: Development Status :: 3 - Alpha
Classifier: Intended Audience :: Science/Research
Classifier: Intended Audience :: Education
Classifier: Topic :: Scientific/Engineering
Classifier: License :: OSI Approved :: GNU General Public License v2 (GPLv2)
Classifier: Programming Language :: Python
Classifier: Programming Language :: Python :: 3
Classifier: Programming Language :: Python :: 3.6
Requires-Python: >=3.6
Provides-Extra: doc
Provides-Extra: parallel
Requires-Dist: fluidsim
Provides-Extra: doc
Requires-Dist: Sphinx (>=1.1); extra == 'doc'
Requires-Dist: numpydoc; extra == 'doc'
Provides-Extra: parallel
Requires-Dist: mpi4py; extra == 'parallel'
